MANIFEST.in
README.rst
requirements.txt
setup.py
src/s3tos3backup/PkgInfo.py
src/s3tos3backup/__init__.py
src/s3tos3backup/backup.py
src/s3tos3backup/copy.py
src/s3tos3backup/remove.py
src/s3tos3backup/runner.py
src/s3tos3backup/worker.py
src/s3tos3backup.egg-info/PKG-INFO
src/s3tos3backup.egg-info/SOURCES.txt
src/s3tos3backup.egg-info/dependency_links.txt
src/s3tos3backup.egg-info/entry_points.txt
src/s3tos3backup.egg-info/not-zip-safe
src/s3tos3backup.egg-info/top_level.txt
src/s3tos3backup/tests/__init__.py
src/s3tos3backup/tests/compat.py
src/s3tos3backup/tests/test_operations.py
src/s3tos3backup/tests/test_runner.py