Metadata-Version: 1.1
Name: s3tos3backup
Version: 1.0
Summary: S3 To S3 Backup
Home-page: https://github.com/YD-Technology/s3tos3backup
Author: YD Technology
Author-email: team@ydtechnology.com
License: MIT
Platform: UNKNOWN
Classifier: License :: OSI Approved :: MIT License
Classifier: Intended Audience :: Developers
Classifier: Intended Audience :: System Administrators
Classifier: Operating System :: OS Independent
Classifier: Programming Language :: Python
